ros2bagsend/__init__.py
ros2bagsend/_version.py
ros2bagsend/main.py
ros2bagsend-1.1.2.dist-info/LICENSE
ros2bagsend-1.1.2.dist-info/METADATA
ros2bagsend-1.1.2.dist-info/WHEEL
ros2bagsend-1.1.2.dist-info/entry_points.txt
ros2bagsend-1.1.2.dist-info/top_level.txt
ros2bagsend-1.1.2.dist-info/RECORD
