Metadata-Version: 2.1
Name: ros2bagsend
Version: 1.1.2
Summary: A tool that uses simple logic to send topics recorded in ros2 bag one cycle at a time (not a strict cycle).
Author-email: Katsuya Hyodo <rmsdh122@yahoo.co.jp>
License: MIT License
Project-URL: Homepage, https://github.com/PINTO0309/ros2bagsend
Classifier: Programming Language :: Python :: 3
Requires-Python: >=3.10
License-File: LICENSE
Requires-Dist: rosbag2-py >=0.15.8
